tttorrent/__init__.py
tttorrent/exceptions/common.py
tttorrent/new/client.py
tttorrent/utils/driver.py
tttorrent/utils/image_uploader.py
tt_torrent-1.0.5.dist-info/LICENSE
tt_torrent-1.0.5.dist-info/METADATA
tt_torrent-1.0.5.dist-info/WHEEL
tt_torrent-1.0.5.dist-info/entry_points.txt
tt_torrent-1.0.5.dist-info/RECORD
