Metadata-Version: 2.1
Name: tt-torrent
Version: 1.0.5
Summary: 😈 Daemon to manage torrents through tt-torrent website.
Home-page: https://github.com/SantiiRepair/tt-torrent
License: GPL-3.0
Author: Santiago Ramirez
Author-email: santiirepair@gmail.com
Requires-Python: >=3.10,<4.0
Classifier: License :: OSI Approved :: GNU General Public License v3 (GPLv3)
Classifier: Programming Language :: Python :: 3
Classifier: Programming Language :: Python :: 3.10
Classifier: Programming Language :: Python :: 3.11
Requires-Dist: click (==8.1.7)
Requires-Dist: colorama (==0.4.6)
Requires-Dist: prettytable (==3.9.0)
Requires-Dist: requests (==2.31.0)
Requires-Dist: selenium (>=4.13.0)
Requires-Dist: shutup (==0.2.0)
Requires-Dist: termcolor (==2.3.0)
Project-URL: Repository, https://github.com/SantiiRepair/tt-torrent
